pharmecon/__init__.py
pharmecon/core.py
pharmecon-0.0.1.dist-info/licenses/LICENSE
pharmecon-0.0.1.dist-info/METADATA
pharmecon-0.0.1.dist-info/WHEEL
pharmecon-0.0.1.dist-info/top_level.txt
pharmecon-0.0.1.dist-info/RECORD
