Metadata-Version: 2.4
Name: pharmecon
Version: 0.0.1
Summary: Pharmecon test package
Author-email: Pharmecon Team <team@pharmecon.org>
License: MIT
Project-URL: Homepage, https://github.com/yourusername/pharmecon
Project-URL: Bug Reports, https://github.com/yourusername/pharmecon/issues
Project-URL: Source, https://github.com/yourusername/pharmecon
Keywords: pharmaceutical,economics,healthcare,cost-effectiveness,budget-impact
Classifier: Development Status :: 3 - Alpha
Classifier: Intended Audience :: Healthcare Industry
Classifier: Intended Audience :: Science/Research
Classifier: License :: OSI Approved :: MIT License
Classifier: Operating System :: OS Independent
Classifier: Programming Language :: Python :: 3
Classifier: Programming Language :: Python :: 3.7
Classifier: Programming Language :: Python :: 3.8
Classifier: Programming Language :: Python :: 3.9
Classifier: Programming Language :: Python :: 3.10
Classifier: Programming Language :: Python :: 3.11
Classifier: Topic :: Scientific/Engineering
Classifier: Topic :: Scientific/Engineering :: Medical Science Apps.
Requires-Python: >=3.7
License-File: LICENSE
Requires-Dist: numpy>=1.20.0
Requires-Dist: pandas>=1.3.0
Provides-Extra: dev
Requires-Dist: pytest>=6.0; extra == "dev"
Requires-Dist: black; extra == "dev"
Requires-Dist: flake8; extra == "dev"
Requires-Dist: mypy; extra == "dev"
Dynamic: license-file
